ros_rosidl_dynamic_typesupport-0.3.1.data/data/include/rosidl_dynamic_typesupport/rosidl_dynamic_typesupport/dynamic_message_type_support_struct.h
ros_rosidl_dynamic_typesupport-0.3.1.data/data/include/rosidl_dynamic_typesupport/rosidl_dynamic_typesupport/identifier.h
ros_rosidl_dynamic_typesupport-0.3.1.data/data/include/rosidl_dynamic_typesupport/rosidl_dynamic_typesupport/macros.h
ros_rosidl_dynamic_typesupport-0.3.1.data/data/include/rosidl_dynamic_typesupport/rosidl_dynamic_typesupport/types.h
ros_rosidl_dynamic_typesupport-0.3.1.data/data/include/rosidl_dynamic_typesupport/rosidl_dynamic_typesupport/uchar.h
ros_rosidl_dynamic_typesupport-0.3.1.data/data/include/rosidl_dynamic_typesupport/rosidl_dynamic_typesupport/visibility_control.h
ros_rosidl_dynamic_typesupport-0.3.1.data/data/include/rosidl_dynamic_typesupport/rosidl_dynamic_typesupport/api/dynamic_data.h
ros_rosidl_dynamic_typesupport-0.3.1.data/data/include/rosidl_dynamic_typesupport/rosidl_dynamic_typesupport/api/dynamic_type.h
ros_rosidl_dynamic_typesupport-0.3.1.data/data/include/rosidl_dynamic_typesupport/rosidl_dynamic_typesupport/api/serialization_support.h
ros_rosidl_dynamic_typesupport-0.3.1.data/data/include/rosidl_dynamic_typesupport/rosidl_dynamic_typesupport/api/serialization_support_interface.h
ros_rosidl_dynamic_typesupport-0.3.1.data/data/lib/librosidl_dynamic_typesupport.so
ros_rosidl_dynamic_typesupport-0.3.1.data/data/share/ament_index/resource_index/package_run_dependencies/rosidl_dynamic_typesupport
ros_rosidl_dynamic_typesupport-0.3.1.data/data/share/ament_index/resource_index/packages/rosidl_dynamic_typesupport
ros_rosidl_dynamic_typesupport-0.3.1.data/data/share/ament_index/resource_index/parent_prefix_path/rosidl_dynamic_typesupport
ros_rosidl_dynamic_typesupport-0.3.1.data/data/share/rosidl_dynamic_typesupport/local_setup.bash
ros_rosidl_dynamic_typesupport-0.3.1.data/data/share/rosidl_dynamic_typesupport/local_setup.dsv
ros_rosidl_dynamic_typesupport-0.3.1.dist-info/METADATA
ros_rosidl_dynamic_typesupport-0.3.1.dist-info/WHEEL
ros_rosidl_dynamic_typesupport-0.3.1.dist-info/top_level.txt
ros_rosidl_dynamic_typesupport-0.3.1.dist-info/RECORD
ros_rosidl_dynamic_typesupport-0.3.1.dist-info/licenses/LICENSE
