Metadata-Version: 2.4
Name: ros-rosidl-dynamic-typesupport
Version: 0.3.1
Summary: A ROS package providing a unified runtime interface for dynamic type support, enabling creation, reflection, and introspection of dynamic data.
License-File: LICENSE
Requires-Dist: ros-rcutils~=6.9.8
Requires-Dist: ros-rosidl-runtime-c~=4.9.5
Dynamic: description
Dynamic: description-content-type
Dynamic: license-file
Dynamic: requires-dist
Dynamic: summary
